LICENSE
README.md
setup.py
madpy/__init__.py
madpy/amplitude.py
madpy/checks.py
madpy/config.py
madpy/duration.py
madpy/noise.py
madpy/plotting/__init__.py
madpy/plotting/amp.py
madpy/plotting/dur.py
madpy/plotting/params.py
madpy/plotting/utils.py
madpy/tests/__init__.py
madpy/tests/test_amplitude.py
madpy/tests/test_checks.py
madpy/tests/test_duration.py
madpy/tests/test_noise.py
madpy/tests/testdata/config.py
madpy/tests/testdata/generate_data.py
madpy_seis.egg-info/PKG-INFO
madpy_seis.egg-info/SOURCES.txt
madpy_seis.egg-info/dependency_links.txt
madpy_seis.egg-info/requires.txt
madpy_seis.egg-info/top_level.txt